Metadata-Version: 1.0
Name: ffmpeg
Version: 1.3
Summary: ffmpeg python package url [https://github.com/jiashaokun/ffmpeg]
Home-page: https://github.com/jiashaokun/ffmpeg
Author: SkeyJIA
Author-email: 363604236@qq.com
License: MIT Licence
Keywords: python ffmpeg
Platform: any
